LEDSerialExpander.cpython-37m-arm-linux-gnueabihf.so
example.py
LEDSerialExpander-0.2.2.dist-info/LICENSE.txt
LEDSerialExpander-0.2.2.dist-info/METADATA
LEDSerialExpander-0.2.2.dist-info/WHEEL
LEDSerialExpander-0.2.2.dist-info/top_level.txt
LEDSerialExpander-0.2.2.dist-info/RECORD
