Metadata-Version: 2.1
Name: LEDSerialExpander
Version: 0.2.2
Summary: Expander Board Python Driver
Home-page: https://github.com/branko623/LEDSerialExpander
Author: Branko Mirkovic
Author-email: branko623@gmail.com
License: MIT
Project-URL: Documentation, https://github.com/branko623/LEDSerialExpander
Project-URL: Code, https://github.com/branko623/LEDSerialExpander
Project-URL: Issue tracker, https://github.com/branko623/LEDSerialExpander/issues
Platform: UNKNOWN
Classifier: Development Status :: 1 - Planning
Classifier: License :: OSI Approved :: MIT License
Classifier: Intended Audience :: Education
Classifier: Intended Audience :: Science/Research
Classifier: Topic :: Scientific/Engineering
Classifier: Topic :: Scientific/Engineering :: Mathematics
Classifier: Natural Language :: English
Classifier: Operating System :: OS Independent
Classifier: Programming Language :: C
Classifier: Programming Language :: Cython
Classifier: Programming Language :: Python
Classifier: Programming Language :: Python :: 3
Classifier: Programming Language :: Python :: 3.4
Classifier: Programming Language :: Python :: 3.5
Classifier: Programming Language :: Python :: 3.6
Classifier: Programming Language :: Python :: 3.7
Classifier: Programming Language :: Python :: 3 :: Only
Classifier: Programming Language :: Python :: Implementation :: CPython
Requires-Python: >=3.4
Requires-Dist: pyserial (>=3.4)
